{"rajaongkir":{"query":{"city":"103"},"status":{"code":200,"description":"OK"},"results":[{"subdistrict_id":"1379","province_id":"9","province":"Jawa Barat","city_id":"103","city":"Ciamis","type":"Kabupaten","subdistrict_name":"Banjarsari"},{"subdistrict_id":"1380","province_id":"9","province":"Jawa Barat","city_id":"103","city":"Ciamis","type":"Kabupaten","subdistrict_name":"Baregbeg"},{"subdistrict_id":"1381","province_id":"9","province":"Jawa Barat","city_id":"103","city":"Ciamis","type":"Kabupaten","subdistrict_name":"Ciamis"},{"subdistrict_id":"1382","province_id":"9","province":"Jawa Barat","city_id":"103","city":"Ciamis","type":"Kabupaten","subdistrict_name":"Cidolog"},{"subdistrict_id":"1383","province_id":"9","province":"Jawa Barat","city_id":"103","city":"Ciamis","type":"Kabupaten","subdistrict_name":"Cihaurbeuti"},{"subdistrict_id":"1384","province_id":"9","province":"Jawa Barat","city_id":"103","city":"Ciamis","type":"Kabupaten","subdistrict_name":"Cijeungjing"},{"subdistrict_id":"1385","province_id":"9","province":"Jawa Barat","city_id":"103","city":"Ciamis","type":"Kabupaten","subdistrict_name":"Cikoneng"},{"subdistrict_id":"1386","province_id":"9","province":"Jawa Barat","city_id":"103","city":"Ciamis","type":"Kabupaten","subdistrict_name":"Cimaragas"},{"subdistrict_id":"1387","province_id":"9","province":"Jawa Barat","city_id":"103","city":"Ciamis","type":"Kabupaten","subdistrict_name":"Cipaku"},{"subdistrict_id":"1388","province_id":"9","province":"Jawa Barat","city_id":"103","city":"Ciamis","type":"Kabupaten","subdistrict_name":"Cisaga"},{"subdistrict_id":"1389","province_id":"9","province":"Jawa Barat","city_id":"103","city":"Ciamis","type":"Kabupaten","subdistrict_name":"Jatinagara"},{"subdistrict_id":"1390","province_id":"9","province":"Jawa Barat","city_id":"103","city":"Ciamis","type":"Kabupaten","subdistrict_name":"Kawali"},{"subdistrict_id":"1391","province_id":"9","province":"Jawa Barat","city_id":"103","city":"Ciamis","type":"Kabupaten","subdistrict_name":"Lakbok"},{"subdistrict_id":"1392","province_id":"9","province":"Jawa Barat","city_id":"103","city":"Ciamis","type":"Kabupaten","subdistrict_name":"Lumbung"},{"subdistrict_id":"1393","province_id":"9","province":"Jawa Barat","city_id":"103","city":"Ciamis","type":"Kabupaten","subdistrict_name":"Pamarican"},{"subdistrict_id":"1394","province_id":"9","province":"Jawa Barat","city_id":"103","city":"Ciamis","type":"Kabupaten","subdistrict_name":"Panawangan"},{"subdistrict_id":"1395","province_id":"9","province":"Jawa Barat","city_id":"103","city":"Ciamis","type":"Kabupaten","subdistrict_name":"Panjalu"},{"subdistrict_id":"1396","province_id":"9","province":"Jawa Barat","city_id":"103","city":"Ciamis","type":"Kabupaten","subdistrict_name":"Panumbangan"},{"subdistrict_id":"1397","province_id":"9","province":"Jawa Barat","city_id":"103","city":"Ciamis","type":"Kabupaten","subdistrict_name":"Purwadadi"},{"subdistrict_id":"1398","province_id":"9","province":"Jawa Barat","city_id":"103","city":"Ciamis","type":"Kabupaten","subdistrict_name":"Rajadesa"},{"subdistrict_id":"1399","province_id":"9","province":"Jawa Barat","city_id":"103","city":"Ciamis","type":"Kabupaten","subdistrict_name":"Rancah"},{"subdistrict_id":"1400","province_id":"9","province":"Jawa Barat","city_id":"103","city":"Ciamis","type":"Kabupaten","subdistrict_name":"Sadananya"},{"subdistrict_id":"1401","province_id":"9","province":"Jawa Barat","city_id":"103","city":"Ciamis","type":"Kabupaten","subdistrict_name":"Sindangkasih"},{"subdistrict_id":"1402","province_id":"9","province":"Jawa Barat","city_id":"103","city":"Ciamis","type":"Kabupaten","subdistrict_name":"Sukadana"},{"subdistrict_id":"1403","province_id":"9","province":"Jawa Barat","city_id":"103","city":"Ciamis","type":"Kabupaten","subdistrict_name":"Sukamantri"},{"subdistrict_id":"1404","province_id":"9","province":"Jawa Barat","city_id":"103","city":"Ciamis","type":"Kabupaten","subdistrict_name":"Tambaksari"}]}}