{"rajaongkir":{"query":{"city":"12"},"status":{"code":200,"description":"OK"},"results":[{"subdistrict_id":"176","province_id":"32","province":"Sumatera Barat","city_id":"12","city":"Agam","type":"Kabupaten","subdistrict_name":"Ampek Nagari (IV Nagari )"},{"subdistrict_id":"177","province_id":"32","province":"Sumatera Barat","city_id":"12","city":"Agam","type":"Kabupaten","subdistrict_name":"Banuhampu"},{"subdistrict_id":"178","province_id":"32","province":"Sumatera Barat","city_id":"12","city":"Agam","type":"Kabupaten","subdistrict_name":"Baso"},{"subdistrict_id":"179","province_id":"32","province":"Sumatera Barat","city_id":"12","city":"Agam","type":"Kabupaten","subdistrict_name":"Candung"},{"subdistrict_id":"180","province_id":"32","province":"Sumatera Barat","city_id":"12","city":"Agam","type":"Kabupaten","subdistrict_name":"IV Angkat Candung (Ampek Angkek)"},{"subdistrict_id":"181","province_id":"32","province":"Sumatera Barat","city_id":"12","city":"Agam","type":"Kabupaten","subdistrict_name":"IV Koto (Ampek Koto)"},{"subdistrict_id":"182","province_id":"32","province":"Sumatera Barat","city_id":"12","city":"Agam","type":"Kabupaten","subdistrict_name":"Kamang Magek"},{"subdistrict_id":"183","province_id":"32","province":"Sumatera Barat","city_id":"12","city":"Agam","type":"Kabupaten","subdistrict_name":"Lubuk Basung"},{"subdistrict_id":"184","province_id":"32","province":"Sumatera Barat","city_id":"12","city":"Agam","type":"Kabupaten","subdistrict_name":"Malakak"},{"subdistrict_id":"185","province_id":"32","province":"Sumatera Barat","city_id":"12","city":"Agam","type":"Kabupaten","subdistrict_name":"Matur"},{"subdistrict_id":"186","province_id":"32","province":"Sumatera Barat","city_id":"12","city":"Agam","type":"Kabupaten","subdistrict_name":"Palembayan"},{"subdistrict_id":"187","province_id":"32","province":"Sumatera Barat","city_id":"12","city":"Agam","type":"Kabupaten","subdistrict_name":"Palupuh"},{"subdistrict_id":"188","province_id":"32","province":"Sumatera Barat","city_id":"12","city":"Agam","type":"Kabupaten","subdistrict_name":"Sungai Pua (Puar)"},{"subdistrict_id":"189","province_id":"32","province":"Sumatera Barat","city_id":"12","city":"Agam","type":"Kabupaten","subdistrict_name":"Tanjung Mutiara"},{"subdistrict_id":"190","province_id":"32","province":"Sumatera Barat","city_id":"12","city":"Agam","type":"Kabupaten","subdistrict_name":"Tanjung Raya"},{"subdistrict_id":"191","province_id":"32","province":"Sumatera Barat","city_id":"12","city":"Agam","type":"Kabupaten","subdistrict_name":"Tilatang Kamang"}]}}