{"rajaongkir":{"query":{"city":"122"},"status":{"code":200,"description":"OK"},"results":[{"subdistrict_id":"1650","province_id":"23","province":"Nusa Tenggara Timur (NTT)","city_id":"122","city":"Ende","type":"Kabupaten","subdistrict_name":"Detukeli"},{"subdistrict_id":"1651","province_id":"23","province":"Nusa Tenggara Timur (NTT)","city_id":"122","city":"Ende","type":"Kabupaten","subdistrict_name":"Detusoko"},{"subdistrict_id":"1652","province_id":"23","province":"Nusa Tenggara Timur (NTT)","city_id":"122","city":"Ende","type":"Kabupaten","subdistrict_name":"Ende"},{"subdistrict_id":"1653","province_id":"23","province":"Nusa Tenggara Timur (NTT)","city_id":"122","city":"Ende","type":"Kabupaten","subdistrict_name":"Ende Selatan"},{"subdistrict_id":"1654","province_id":"23","province":"Nusa Tenggara Timur (NTT)","city_id":"122","city":"Ende","type":"Kabupaten","subdistrict_name":"Ende Tengah"},{"subdistrict_id":"1655","province_id":"23","province":"Nusa Tenggara Timur (NTT)","city_id":"122","city":"Ende","type":"Kabupaten","subdistrict_name":"Ende Timur"},{"subdistrict_id":"1656","province_id":"23","province":"Nusa Tenggara Timur (NTT)","city_id":"122","city":"Ende","type":"Kabupaten","subdistrict_name":"Ende Utara"},{"subdistrict_id":"1657","province_id":"23","province":"Nusa Tenggara Timur (NTT)","city_id":"122","city":"Ende","type":"Kabupaten","subdistrict_name":"Kelimutu"},{"subdistrict_id":"1658","province_id":"23","province":"Nusa Tenggara Timur (NTT)","city_id":"122","city":"Ende","type":"Kabupaten","subdistrict_name":"Kotabaru"},{"subdistrict_id":"1659","province_id":"23","province":"Nusa Tenggara Timur (NTT)","city_id":"122","city":"Ende","type":"Kabupaten","subdistrict_name":"Lepembusu Kelisoke"},{"subdistrict_id":"1660","province_id":"23","province":"Nusa Tenggara Timur (NTT)","city_id":"122","city":"Ende","type":"Kabupaten","subdistrict_name":"Lio Timur"},{"subdistrict_id":"1661","province_id":"23","province":"Nusa Tenggara Timur (NTT)","city_id":"122","city":"Ende","type":"Kabupaten","subdistrict_name":"Maukaro"},{"subdistrict_id":"1662","province_id":"23","province":"Nusa Tenggara Timur (NTT)","city_id":"122","city":"Ende","type":"Kabupaten","subdistrict_name":"Maurole"},{"subdistrict_id":"1663","province_id":"23","province":"Nusa Tenggara Timur (NTT)","city_id":"122","city":"Ende","type":"Kabupaten","subdistrict_name":"Nangapanda"},{"subdistrict_id":"1664","province_id":"23","province":"Nusa Tenggara Timur (NTT)","city_id":"122","city":"Ende","type":"Kabupaten","subdistrict_name":"Ndona"},{"subdistrict_id":"1665","province_id":"23","province":"Nusa Tenggara Timur (NTT)","city_id":"122","city":"Ende","type":"Kabupaten","subdistrict_name":"Ndona Timur"},{"subdistrict_id":"1666","province_id":"23","province":"Nusa Tenggara Timur (NTT)","city_id":"122","city":"Ende","type":"Kabupaten","subdistrict_name":"Ndori"},{"subdistrict_id":"1667","province_id":"23","province":"Nusa Tenggara Timur (NTT)","city_id":"122","city":"Ende","type":"Kabupaten","subdistrict_name":"Pulau Ende"},{"subdistrict_id":"1668","province_id":"23","province":"Nusa Tenggara Timur (NTT)","city_id":"122","city":"Ende","type":"Kabupaten","subdistrict_name":"Wewaria"},{"subdistrict_id":"1669","province_id":"23","province":"Nusa Tenggara Timur (NTT)","city_id":"122","city":"Ende","type":"Kabupaten","subdistrict_name":"Wolojita"},{"subdistrict_id":"1670","province_id":"23","province":"Nusa Tenggara Timur (NTT)","city_id":"122","city":"Ende","type":"Kabupaten","subdistrict_name":"Wolowaru"}]}}