{"rajaongkir":{"query":{"city":"126"},"status":{"code":200,"description":"OK"},"results":[{"subdistrict_id":"1711","province_id":"9","province":"Jawa Barat","city_id":"126","city":"Garut","type":"Kabupaten","subdistrict_name":"Banjarwangi"},{"subdistrict_id":"1712","province_id":"9","province":"Jawa Barat","city_id":"126","city":"Garut","type":"Kabupaten","subdistrict_name":"Banyuresmi"},{"subdistrict_id":"1713","province_id":"9","province":"Jawa Barat","city_id":"126","city":"Garut","type":"Kabupaten","subdistrict_name":"Bayongbong"},{"subdistrict_id":"1714","province_id":"9","province":"Jawa Barat","city_id":"126","city":"Garut","type":"Kabupaten","subdistrict_name":"Blubur Limbangan"},{"subdistrict_id":"1715","province_id":"9","province":"Jawa Barat","city_id":"126","city":"Garut","type":"Kabupaten","subdistrict_name":"Bungbulang"},{"subdistrict_id":"1716","province_id":"9","province":"Jawa Barat","city_id":"126","city":"Garut","type":"Kabupaten","subdistrict_name":"Caringin"},{"subdistrict_id":"1717","province_id":"9","province":"Jawa Barat","city_id":"126","city":"Garut","type":"Kabupaten","subdistrict_name":"Cibalong"},{"subdistrict_id":"1718","province_id":"9","province":"Jawa Barat","city_id":"126","city":"Garut","type":"Kabupaten","subdistrict_name":"Cibatu"},{"subdistrict_id":"1719","province_id":"9","province":"Jawa Barat","city_id":"126","city":"Garut","type":"Kabupaten","subdistrict_name":"Cibiuk"},{"subdistrict_id":"1720","province_id":"9","province":"Jawa Barat","city_id":"126","city":"Garut","type":"Kabupaten","subdistrict_name":"Cigedug"},{"subdistrict_id":"1721","province_id":"9","province":"Jawa Barat","city_id":"126","city":"Garut","type":"Kabupaten","subdistrict_name":"Cihurip"},{"subdistrict_id":"1722","province_id":"9","province":"Jawa Barat","city_id":"126","city":"Garut","type":"Kabupaten","subdistrict_name":"Cikajang"},{"subdistrict_id":"1723","province_id":"9","province":"Jawa Barat","city_id":"126","city":"Garut","type":"Kabupaten","subdistrict_name":"Cikelet"},{"subdistrict_id":"1724","province_id":"9","province":"Jawa Barat","city_id":"126","city":"Garut","type":"Kabupaten","subdistrict_name":"Cilawu"},{"subdistrict_id":"1725","province_id":"9","province":"Jawa Barat","city_id":"126","city":"Garut","type":"Kabupaten","subdistrict_name":"Cisewu"},{"subdistrict_id":"1726","province_id":"9","province":"Jawa Barat","city_id":"126","city":"Garut","type":"Kabupaten","subdistrict_name":"Cisompet"},{"subdistrict_id":"1727","province_id":"9","province":"Jawa Barat","city_id":"126","city":"Garut","type":"Kabupaten","subdistrict_name":"Cisurupan"},{"subdistrict_id":"1728","province_id":"9","province":"Jawa Barat","city_id":"126","city":"Garut","type":"Kabupaten","subdistrict_name":"Garut Kota"},{"subdistrict_id":"1729","province_id":"9","province":"Jawa Barat","city_id":"126","city":"Garut","type":"Kabupaten","subdistrict_name":"Kadungora"},{"subdistrict_id":"1730","province_id":"9","province":"Jawa Barat","city_id":"126","city":"Garut","type":"Kabupaten","subdistrict_name":"Karangpawitan"},{"subdistrict_id":"1731","province_id":"9","province":"Jawa Barat","city_id":"126","city":"Garut","type":"Kabupaten","subdistrict_name":"Karangtengah"},{"subdistrict_id":"1732","province_id":"9","province":"Jawa Barat","city_id":"126","city":"Garut","type":"Kabupaten","subdistrict_name":"Kersamanah"},{"subdistrict_id":"1733","province_id":"9","province":"Jawa Barat","city_id":"126","city":"Garut","type":"Kabupaten","subdistrict_name":"Leles"},{"subdistrict_id":"1734","province_id":"9","province":"Jawa Barat","city_id":"126","city":"Garut","type":"Kabupaten","subdistrict_name":"Leuwigoong"},{"subdistrict_id":"1735","province_id":"9","province":"Jawa Barat","city_id":"126","city":"Garut","type":"Kabupaten","subdistrict_name":"Malangbong"},{"subdistrict_id":"1736","province_id":"9","province":"Jawa Barat","city_id":"126","city":"Garut","type":"Kabupaten","subdistrict_name":"Mekarmukti"},{"subdistrict_id":"1737","province_id":"9","province":"Jawa Barat","city_id":"126","city":"Garut","type":"Kabupaten","subdistrict_name":"Pakenjeng"},{"subdistrict_id":"1738","province_id":"9","province":"Jawa Barat","city_id":"126","city":"Garut","type":"Kabupaten","subdistrict_name":"Pameungpeuk"},{"subdistrict_id":"1739","province_id":"9","province":"Jawa Barat","city_id":"126","city":"Garut","type":"Kabupaten","subdistrict_name":"Pamulihan"},{"subdistrict_id":"1740","province_id":"9","province":"Jawa Barat","city_id":"126","city":"Garut","type":"Kabupaten","subdistrict_name":"Pangatikan"},{"subdistrict_id":"1741","province_id":"9","province":"Jawa Barat","city_id":"126","city":"Garut","type":"Kabupaten","subdistrict_name":"Pasirwangi"},{"subdistrict_id":"1742","province_id":"9","province":"Jawa Barat","city_id":"126","city":"Garut","type":"Kabupaten","subdistrict_name":"Peundeuy"},{"subdistrict_id":"1743","province_id":"9","province":"Jawa Barat","city_id":"126","city":"Garut","type":"Kabupaten","subdistrict_name":"Samarang"},{"subdistrict_id":"1744","province_id":"9","province":"Jawa Barat","city_id":"126","city":"Garut","type":"Kabupaten","subdistrict_name":"Selaawi"},{"subdistrict_id":"1745","province_id":"9","province":"Jawa Barat","city_id":"126","city":"Garut","type":"Kabupaten","subdistrict_name":"Singajaya"},{"subdistrict_id":"1746","province_id":"9","province":"Jawa Barat","city_id":"126","city":"Garut","type":"Kabupaten","subdistrict_name":"Sucinaraja"},{"subdistrict_id":"1747","province_id":"9","province":"Jawa Barat","city_id":"126","city":"Garut","type":"Kabupaten","subdistrict_name":"Sukaresmi"},{"subdistrict_id":"1748","province_id":"9","province":"Jawa Barat","city_id":"126","city":"Garut","type":"Kabupaten","subdistrict_name":"Sukawening"},{"subdistrict_id":"1749","province_id":"9","province":"Jawa Barat","city_id":"126","city":"Garut","type":"Kabupaten","subdistrict_name":"Talegong"},{"subdistrict_id":"1750","province_id":"9","province":"Jawa Barat","city_id":"126","city":"Garut","type":"Kabupaten","subdistrict_name":"Tarogong Kaler"},{"subdistrict_id":"1751","province_id":"9","province":"Jawa Barat","city_id":"126","city":"Garut","type":"Kabupaten","subdistrict_name":"Tarogong Kidul"},{"subdistrict_id":"1752","province_id":"9","province":"Jawa Barat","city_id":"126","city":"Garut","type":"Kabupaten","subdistrict_name":"Wanaraja"}]}}