{"rajaongkir":{"query":{"city":"38"},"status":{"code":200,"description":"OK"},"results":[{"subdistrict_id":"529","province_id":"28","province":"Sulawesi Selatan","city_id":"38","city":"Bantaeng","type":"Kabupaten","subdistrict_name":"Bantaeng"},{"subdistrict_id":"530","province_id":"28","province":"Sulawesi Selatan","city_id":"38","city":"Bantaeng","type":"Kabupaten","subdistrict_name":"Bissappu"},{"subdistrict_id":"531","province_id":"28","province":"Sulawesi Selatan","city_id":"38","city":"Bantaeng","type":"Kabupaten","subdistrict_name":"Eremerasa"},{"subdistrict_id":"532","province_id":"28","province":"Sulawesi Selatan","city_id":"38","city":"Bantaeng","type":"Kabupaten","subdistrict_name":"Gantarang Keke (Gantareng Keke)"},{"subdistrict_id":"533","province_id":"28","province":"Sulawesi Selatan","city_id":"38","city":"Bantaeng","type":"Kabupaten","subdistrict_name":"Pajukukang"},{"subdistrict_id":"534","province_id":"28","province":"Sulawesi Selatan","city_id":"38","city":"Bantaeng","type":"Kabupaten","subdistrict_name":"Sinoa"},{"subdistrict_id":"535","province_id":"28","province":"Sulawesi Selatan","city_id":"38","city":"Bantaeng","type":"Kabupaten","subdistrict_name":"Tompobulu"},{"subdistrict_id":"536","province_id":"28","province":"Sulawesi Selatan","city_id":"38","city":"Bantaeng","type":"Kabupaten","subdistrict_name":"Uluere"}]}}