{"rajaongkir":{"query":{"city":"385"},"status":{"code":200,"description":"OK"},"results":[{"subdistrict_id":"5346","province_id":"23","province":"Nusa Tenggara Timur (NTT)","city_id":"385","city":"Sabu Raijua","type":"Kabupaten","subdistrict_name":"Hawu Mehara"},{"subdistrict_id":"5347","province_id":"23","province":"Nusa Tenggara Timur (NTT)","city_id":"385","city":"Sabu Raijua","type":"Kabupaten","subdistrict_name":"Raijua"},{"subdistrict_id":"5348","province_id":"23","province":"Nusa Tenggara Timur (NTT)","city_id":"385","city":"Sabu Raijua","type":"Kabupaten","subdistrict_name":"Sabu Barat"},{"subdistrict_id":"5349","province_id":"23","province":"Nusa Tenggara Timur (NTT)","city_id":"385","city":"Sabu Raijua","type":"Kabupaten","subdistrict_name":"Sabu Liae"},{"subdistrict_id":"5350","province_id":"23","province":"Nusa Tenggara Timur (NTT)","city_id":"385","city":"Sabu Raijua","type":"Kabupaten","subdistrict_name":"Sabu Tengah"},{"subdistrict_id":"5351","province_id":"23","province":"Nusa Tenggara Timur (NTT)","city_id":"385","city":"Sabu Raijua","type":"Kabupaten","subdistrict_name":"Sabu Timur"}]}}