{"rajaongkir":{"query":{"city":"416"},"status":{"code":200,"description":"OK"},"results":[{"subdistrict_id":"5739","province_id":"28","province":"Sulawesi Selatan","city_id":"416","city":"Sinjai","type":"Kabupaten","subdistrict_name":"Bulupoddo"},{"subdistrict_id":"5740","province_id":"28","province":"Sulawesi Selatan","city_id":"416","city":"Sinjai","type":"Kabupaten","subdistrict_name":"Pulau Sembilan"},{"subdistrict_id":"5741","province_id":"28","province":"Sulawesi Selatan","city_id":"416","city":"Sinjai","type":"Kabupaten","subdistrict_name":"Sinjai Barat"},{"subdistrict_id":"5742","province_id":"28","province":"Sulawesi Selatan","city_id":"416","city":"Sinjai","type":"Kabupaten","subdistrict_name":"Sinjai Borong"},{"subdistrict_id":"5743","province_id":"28","province":"Sulawesi Selatan","city_id":"416","city":"Sinjai","type":"Kabupaten","subdistrict_name":"Sinjai Selatan"},{"subdistrict_id":"5744","province_id":"28","province":"Sulawesi Selatan","city_id":"416","city":"Sinjai","type":"Kabupaten","subdistrict_name":"Sinjai Tengah"},{"subdistrict_id":"5745","province_id":"28","province":"Sulawesi Selatan","city_id":"416","city":"Sinjai","type":"Kabupaten","subdistrict_name":"Sinjai Timur"},{"subdistrict_id":"5746","province_id":"28","province":"Sulawesi Selatan","city_id":"416","city":"Sinjai","type":"Kabupaten","subdistrict_name":"Sinjai Utara"},{"subdistrict_id":"5747","province_id":"28","province":"Sulawesi Selatan","city_id":"416","city":"Sinjai","type":"Kabupaten","subdistrict_name":"Tellu Limpoe"}]}}