{"rajaongkir":{"query":{"city":"498"},"status":{"code":200,"description":"OK"},"results":[{"subdistrict_id":"6910","province_id":"10","province":"Jawa Tengah","city_id":"498","city":"Wonosobo","type":"Kabupaten","subdistrict_name":"Garung"},{"subdistrict_id":"6911","province_id":"10","province":"Jawa Tengah","city_id":"498","city":"Wonosobo","type":"Kabupaten","subdistrict_name":"Kalibawang"},{"subdistrict_id":"6912","province_id":"10","province":"Jawa Tengah","city_id":"498","city":"Wonosobo","type":"Kabupaten","subdistrict_name":"Kalikajar"},{"subdistrict_id":"6913","province_id":"10","province":"Jawa Tengah","city_id":"498","city":"Wonosobo","type":"Kabupaten","subdistrict_name":"Kaliwiro"},{"subdistrict_id":"6914","province_id":"10","province":"Jawa Tengah","city_id":"498","city":"Wonosobo","type":"Kabupaten","subdistrict_name":"Kejajar"},{"subdistrict_id":"6915","province_id":"10","province":"Jawa Tengah","city_id":"498","city":"Wonosobo","type":"Kabupaten","subdistrict_name":"Kepil"},{"subdistrict_id":"6916","province_id":"10","province":"Jawa Tengah","city_id":"498","city":"Wonosobo","type":"Kabupaten","subdistrict_name":"Kertek"},{"subdistrict_id":"6917","province_id":"10","province":"Jawa Tengah","city_id":"498","city":"Wonosobo","type":"Kabupaten","subdistrict_name":"Leksono"},{"subdistrict_id":"6918","province_id":"10","province":"Jawa Tengah","city_id":"498","city":"Wonosobo","type":"Kabupaten","subdistrict_name":"Mojotengah"},{"subdistrict_id":"6919","province_id":"10","province":"Jawa Tengah","city_id":"498","city":"Wonosobo","type":"Kabupaten","subdistrict_name":"Sapuran"},{"subdistrict_id":"6920","province_id":"10","province":"Jawa Tengah","city_id":"498","city":"Wonosobo","type":"Kabupaten","subdistrict_name":"Selomerto"},{"subdistrict_id":"6921","province_id":"10","province":"Jawa Tengah","city_id":"498","city":"Wonosobo","type":"Kabupaten","subdistrict_name":"Sukoharjo"},{"subdistrict_id":"6922","province_id":"10","province":"Jawa Tengah","city_id":"498","city":"Wonosobo","type":"Kabupaten","subdistrict_name":"Wadaslintang"},{"subdistrict_id":"6923","province_id":"10","province":"Jawa Tengah","city_id":"498","city":"Wonosobo","type":"Kabupaten","subdistrict_name":"Watumalang"},{"subdistrict_id":"6924","province_id":"10","province":"Jawa Tengah","city_id":"498","city":"Wonosobo","type":"Kabupaten","subdistrict_name":"Wonosobo"}]}}