{"rajaongkir":{"query":{"city":"60"},"status":{"code":200,"description":"OK"},"results":[{"subdistrict_id":"807","province_id":"26","province":"Riau","city_id":"60","city":"Bengkalis","type":"Kabupaten","subdistrict_name":"Bantan"},{"subdistrict_id":"808","province_id":"26","province":"Riau","city_id":"60","city":"Bengkalis","type":"Kabupaten","subdistrict_name":"Bengkalis"},{"subdistrict_id":"809","province_id":"26","province":"Riau","city_id":"60","city":"Bengkalis","type":"Kabupaten","subdistrict_name":"Bukit Batu"},{"subdistrict_id":"810","province_id":"26","province":"Riau","city_id":"60","city":"Bengkalis","type":"Kabupaten","subdistrict_name":"Mandau"},{"subdistrict_id":"811","province_id":"26","province":"Riau","city_id":"60","city":"Bengkalis","type":"Kabupaten","subdistrict_name":"Pinggir"},{"subdistrict_id":"812","province_id":"26","province":"Riau","city_id":"60","city":"Bengkalis","type":"Kabupaten","subdistrict_name":"Rupat"},{"subdistrict_id":"813","province_id":"26","province":"Riau","city_id":"60","city":"Bengkalis","type":"Kabupaten","subdistrict_name":"Rupat Utara"},{"subdistrict_id":"814","province_id":"26","province":"Riau","city_id":"60","city":"Bengkalis","type":"Kabupaten","subdistrict_name":"Siak Kecil"}]}}